acceptanceutils/__init__.py
acceptanceutils/surjection.py
acceptanceutils/watcher.py
acceptanceutils-0.1.2.dist-info/DESCRIPTION.rst
acceptanceutils-0.1.2.dist-info/METADATA
acceptanceutils-0.1.2.dist-info/RECORD
acceptanceutils-0.1.2.dist-info/WHEEL
acceptanceutils-0.1.2.dist-info/metadata.json
acceptanceutils-0.1.2.dist-info/top_level.txt
