Metadata-Version: 2.0
Name: acceptanceutils
Version: 0.1.2
Summary: Generic acceptance testing utils.
Home-page: https://github.com/Brian-Williams/acceptanceutils
Author: Brian Williams
Author-email: briancmwilliams@gmail.com
License: MIT
Keywords: testing acceptance
Platform: UNKNOWN
Classifier: Development Status :: 3 - Alpha
Classifier: Intended Audience :: Developers
Classifier: Topic :: Software Development :: Build Tools
Classifier: License :: OSI Approved :: MIT License
Classifier: Programming Language :: Python :: 2
Classifier: Programming Language :: Python :: 2.7
Classifier: Programming Language :: Python :: 3
Classifier: Programming Language :: Python :: 3.5
Classifier: Programming Language :: Python :: Implementation :: PyPy
Provides-Extra: test
Requires-Dist: flake8; extra == 'test'
Requires-Dist: pytest (>=2.9.0); extra == 'test'
Requires-Dist: six; extra == 'test'
